{"photos":[
	{
		"image":"images/model1.jpg",
		"class":"model1",
		"alt":"model1"
	},
	{
		"image":"images/model2.jpg",
		"class":"model2",
		"alt":"model2"
	},
	{
		"image":"images/model3.jpg",
		"class":"model3",
		"alt":"model3"
    },
    {
		"image":"images/model4.jpg",
		"class":"model4",
		"alt":"model4"
    },	{
		"image":"images/model5.jpg",
		"class":"model5",
		"alt":"model5"
    },	{
		"image":"images/model6.jpg",
		"class":"model6",
		"alt":"model6"
    },	{
		"image":"images/model7.jpg",
		"class":"model7",
		"alt":"model7"
    },	{
		"image":"images/model8.jpg",
		"class":"model8",
		"alt":"model8"
    },	{
		"image":"images/model9.jpg",
		"class":"model9",
		"alt":"model9"
    },	{
		"image":"images/model10.jpg",
		"class":"model10",
		"alt":"model10"
    },	{
		"image":"images/model11.jpg",
		"class":"model11",
		"alt":"model11"
    },	{
		"image":"images/model12.jpg",
		"class":"model12",
		"alt":"model12"
    },	{
		"image":"images/model13.jpg",
		"class":"model13",
		"alt":"model13"
    },	{
		"image":"images/model14.jpg",
		"class":"model14",
		"alt":"model14"
    },	{
		"image":"images/model15.jpg",
		"class":"model15",
		"alt":"model15"
    },	{
		"image":"images/model16.jpg",
		"class":"model16",
		"alt":"model16"
    },	{
		"image":"images/model17.jpg",
		"class":"model17",
		"alt":"model17"
    },	{
		"image":"images/model18.jpg",
		"class":"model18",
		"alt":"model18"
    },	{
		"image":"images/model19.jpg",
		"class":"model19",
		"alt":"model19"
    },	{
		"image":"images/model20.jpg",
		"class":"model20",
		"alt":"model20"
    },	{
		"image":"images/model21.jpg",
		"class":"model21",
		"alt":"model21"
    },	{
		"image":"images/model22.jpg",
		"class":"model22",
		"alt":"model22"
    },	{
		"image":"images/model23.jpg",
		"class":"model23",
		"alt":"model23"
    }
    
]}